{
 "artist": {
  "mbid": "a46ed0f8-b68e-4f78-8d90-92f852607d89",
  "Image": [
   {
    "size": "small",
    "#text": "https://lastfm.freetls.fastly.net/i/u/174s/13bdba27a45755c764631c767f27f855.jpg"
   },
   {
    "size": "medium",
    "#text": "https://lastfm.freetls.fastly.net/i/u/300x300/13bdba27a45755c764631c767f27f855.jpg"
   },
   {
    "size": "large",
    "#text": "https://lastfm.freetls.fastly.net/i/u/470x470/13bdba27a45755c764631c767f27f855.jpg"
   }
  ],
  "#text": "Hobo Johnson"
 },
 "streamable": "0",
 "mtableStatus := Status{Table: *tableDescription.Table.TableName": "",
 "album": {
  "mbid": "",
  "#text": "The Rise of Hobo Johnson [Explicit]"
 },
 "name": "The Ending [Explicit]",
 "url": "https://www.last.fm/music/Hobo+Johnson/_/The+Ending+%5BExplicit%5D",
 "date": {
  "uts": "1666993495",
  "#text": "28 Oct 2022, 21:44"
 },
 "image": [
  {
   "size": "small",
   "#text": "https://lastfm.freetls.fastly.net/i/u/34s/470d018d0428d633f2e8169c66057a3d.jpg"
  },
  {
   "size": "medium",
   "#text": "https://lastfm.freetls.fastly.net/i/u/64s/470d018d0428d633f2e8169c66057a3d.jpg"
  },
  {
   "size": "large",
   "#text": "https://lastfm.freetls.fastly.net/i/u/174s/470d018d0428d633f2e8169c66057a3d.jpg"
  },
  {
   "size": "extralarge",
   "#text": "https://lastfm.freetls.fastly.net/i/u/300x300/470d018d0428d633f2e8169c66057a3d.jpg"
  }
 ]
}